Metadata-Version: 1.1
Name: dpcontracts
Version: 0.4.0
Summary: A simple implementation of contracts for Python.
Home-page: https://github.com/deadpixi/contracts
Author: Rob King
Author-email: jking@deadpixi.com
License: https://www.gnu.org/licenses/lgpl.txt
Platform: UNKNOWN
Classifier: Development Status :: 3 - Alpha
Classifier: Intended Audience :: Developers
Classifier: License :: OSI Approved :: GNU Lesser General Public License v3 or later (LGPLv3+)
Classifier: Operating System :: OS Independent
Classifier: Programming Language :: Python
Classifier: Programming Language :: Python :: 2
Classifier: Programming Language :: Python :: 3
Classifier: Topic :: Software Development :: Libraries
